win10toast/__init__.py
win10toast/__main__.py
win10toast/data/python.ico
win10toast_withsound-0.9.dist-info/LICENSE
win10toast_withsound-0.9.dist-info/METADATA
win10toast_withsound-0.9.dist-info/WHEEL
win10toast_withsound-0.9.dist-info/top_level.txt
win10toast_withsound-0.9.dist-info/RECORD
