Metadata-Version: 1.1
Name: win10toast-withsound
Version: 0.9
Summary: An easy-to-use Python library for displaying Windows 10 Toast Notifications
Home-page: https://github.com/Tazmondo/Windows-10-Toast-Notifications-with-sound-option
Author: taz
Author-email: UNKNOWN
License: BSD
Platform: UNKNOWN
Classifier: Development Status :: 3 - Alpha
Classifier: Topic :: Utilities
Classifier: Operating System :: Microsoft
Classifier: Environment :: Win32 (MS Windows)
Classifier: License :: OSI Approved :: MIT License
